[{"timestamp": "2024-01-30T19:07:56.594664", "age": 32, "gender": "Male", "bounding_box": {"x1": 130, "y1": 130, "x2": 439, "y2": 439}},{"timestamp": "2024-01-30T19:07:56.665741", "age": 32, "gender": "Male", "bounding_box": {"x1": 130, "y1": 130, "x2": 439, "y2": 439}},{"timestamp": "2024-01-30T19:07:56.732041", "age": 31, "gender": "Male", "bounding_box": {"x1": 130, "y1": 130, "x2": 439, "y2": 439}},{"timestamp": "2024-01-30T19:07:56.798478", "age": 31, "gender": "Male", "bounding_box": {"x1": 165, "y1": 136, "x2": 423, "y2": 394}},{"timestamp": "2024-01-30T19:07:56.867137", "age": 31, "gender": "Male", "bounding_box": {"x1": 165, "y1": 136, "x2": 423, "y2": 394}},{"timestamp": "2024-01-30T19:07:56.933751", "age": 31, "gender": "Male", "bounding_box": {"x1": 165, "y1": 136, "x2": 423, "y2": 394}},{"timestamp": "2024-01-30T19:07:57.000576", "age": 31, "gender": "Male", "bounding_box": {"x1": 165, "y1": 136, "x2": 423, "y2": 394}},{"timestamp": "2024-01-30T19:07:57.067414", "age": 31, "gender": "Male", "bounding_box": {"x1": 165, "y1": 136, "x2": 423, "y2": 394}},{"timestamp": "2024-01-30T19:07:57.138069", "age": 33, "gender": "Male", "bounding_box": {"x1": 165, "y1": 136, "x2": 423, "y2": 394}},{"timestamp": "2024-01-30T19:07:57.205626", "age": 35, "gender": "Male", "bounding_box": {"x1": 165, "y1": 136, "x2": 423, "y2": 394}},{"timestamp": "2024-01-30T19:07:57.272975", "age": 35, "gender": "Male", "bounding_box": {"x1": 165, "y1": 136, "x2": 423, "y2": 394}},{"timestamp": "2024-01-30T19:07:57.339700", "age": 34, "gender": "Male", "bounding_box": {"x1": 165, "y1": 136, "x2": 423, "y2": 394}},{"timestamp": "2024-01-30T19:07:57.406140", "age": 34, "gender": "Male", "bounding_box": {"x1": 165, "y1": 136, "x2": 423, "y2": 394}},{"timestamp": "2024-01-30T19:07:57.472660", "age": 35, "gender": "Male", "bounding_box": {"x1": 165, "y1": 136, "x2": 423, "y2": 394}},{"timestamp": "2024-01-30T19:07:57.539191", "age": 34, "gender": "Male", "bounding_box": {"x1": 165, "y1": 136, "x2": 423, "y2": 394}},{"timestamp": "2024-01-30T19:07:57.609637", "age": 35, "gender": "Male", "bounding_box": {"x1": 165, "y1": 136, "x2": 423, "y2": 394}},{"timestamp": "2024-01-30T19:07:57.682023", "age": 35, "gender": "Male", "bounding_box": {"x1": 165, "y1": 136, "x2": 423, "y2": 394}},{"timestamp": "2024-01-30T19:07:57.749095", "age": 34, "gender": "Male", "bounding_box": {"x1": 165, "y1": 136, "x2": 423, "y2": 394}},{"timestamp": "2024-01-30T19:07:57.815169", "age": 34, "gender": "Male", "bounding_box": {"x1": 165, "y1": 136, "x2": 423, "y2": 394}},{"timestamp": "2024-01-30T19:07:57.883141", "age": 34, "gender": "Male", "bounding_box": {"x1": 165, "y1": 136, "x2": 423, "y2": 394}},{"timestamp": "2024-01-30T19:07:57.949497", "age": 35, "gender": "Male", "bounding_box": {"x1": 165, "y1": 136, "x2": 423, "y2": 394}},{"timestamp": "2024-01-30T19:07:58.018967", "age": 35, "gender": "Male", "bounding_box": {"x1": 165, "y1": 136, "x2": 423, "y2": 394}},{"timestamp": "2024-01-30T19:07:58.086483", "age": 33, "gender": "Male", "bounding_box": {"x1": 165, "y1": 136, "x2": 423, "y2": 394}},{"timestamp": "2024-01-30T19:07:58.153626", "age": 36, "gender": "Male", "bounding_box": {"x1": 165, "y1": 136, "x2": 423, "y2": 394}},{"timestamp": "2024-01-30T19:07:58.219854", "age": 34, "gender": "Male", "bounding_box": {"x1": 165, "y1": 136, "x2": 423, "y2": 394}},{"timestamp": "2024-01-30T19:07:58.286331", "age": 35, "gender": "Male", "bounding_box": {"x1": 165, "y1": 136, "x2": 423, "y2": 394}},{"timestamp": "2024-01-30T19:07:58.352761", "age": 35, "gender": "Male", "bounding_box": {"x1": 165, "y1": 136, "x2": 423, "y2": 394}},{"timestamp": "2024-01-30T19:07:58.422055", "age": 35, "gender": "Male", "bounding_box": {"x1": 165, "y1": 136, "x2": 423, "y2": 394}},{"timestamp": "2024-01-30T19:07:58.488924", "age": 35, "gender": "Male", "bounding_box": {"x1": 165, "y1": 136, "x2": 423, "y2": 394}},{"timestamp": "2024-01-30T19:07:58.556282", "age": 35, "gender": "Male", "bounding_box": {"x1": 165, "y1": 136, "x2": 423, "y2": 394}},{"timestamp": "2024-01-30T19:07:58.622645", "age": 34, "gender": "Male", "bounding_box": {"x1": 165, "y1": 136, "x2": 423, "y2": 394}},{"timestamp": "2024-01-30T19:07:58.689364", "age": 34, "gender": "Male", "bounding_box": {"x1": 165, "y1": 136, "x2": 423, "y2": 394}},{"timestamp": "2024-01-30T19:07:58.757401", "age": 33, "gender": "Male", "bounding_box": {"x1": 185, "y1": 137, "x2": 400, "y2": 352}},{"timestamp": "2024-01-30T19:07:58.824270", "age": 32, "gender": "Male", "bounding_box": {"x1": 185, "y1": 137, "x2": 400, "y2": 352}},{"timestamp": "2024-01-30T19:07:58.892523", "age": 31, "gender": "Male", "bounding_box": {"x1": 185, "y1": 137, "x2": 400, "y2": 352}},{"timestamp": "2024-01-30T19:07:58.958965", "age": 31, "gender": "Male", "bounding_box": {"x1": 185, "y1": 137, "x2": 400, "y2": 352}},{"timestamp": "2024-01-30T19:07:59.025199", "age": 31, "gender": "Male", "bounding_box": {"x1": 185, "y1": 137, "x2": 400, "y2": 352}},{"timestamp": "2024-01-30T19:07:59.091516", "age": 31, "gender": "Male", "bounding_box": {"x1": 185, "y1": 137, "x2": 400, "y2": 352}},{"timestamp": "2024-01-30T19:07:59.160100", "age": 32, "gender": "Male", "bounding_box": {"x1": 185, "y1": 137, "x2": 400, "y2": 352}},{"timestamp": "2024-01-30T19:07:59.226569", "age": 32, "gender": "Male", "bounding_box": {"x1": 185, "y1": 137, "x2": 400, "y2": 352}},{"timestamp": "2024-01-30T19:07:59.293043", "age": 33, "gender": "Male", "bounding_box": {"x1": 185, "y1": 137, "x2": 400, "y2": 352}},{"timestamp": "2024-01-30T19:07:59.359919", "age": 33, "gender": "Male", "bounding_box": {"x1": 185, "y1": 137, "x2": 400, "y2": 352}},{"timestamp": "2024-01-30T19:07:59.426510", "age": 34, "gender": "Male", "bounding_box": {"x1": 185, "y1": 137, "x2": 400, "y2": 352}},{"timestamp": "2024-01-30T19:07:59.493496", "age": 33, "gender": "Male", "bounding_box": {"x1": 185, "y1": 137, "x2": 400, "y2": 352}},{"timestamp": "2024-01-30T19:07:59.560380", "age": 33, "gender": "Male", "bounding_box": {"x1": 185, "y1": 137, "x2": 400, "y2": 352}},{"timestamp": "2024-01-30T19:07:59.632581", "age": 34, "gender": "Male", "bounding_box": {"x1": 185, "y1": 137, "x2": 400, "y2": 352}},{"timestamp": "2024-01-30T19:07:59.699028", "age": 36, "gender": "Male", "bounding_box": {"x1": 185, "y1": 137, "x2": 400, "y2": 352}},{"timestamp": "2024-01-30T19:07:59.774866", "age": 35, "gender": "Male", "bounding_box": {"x1": 185, "y1": 137, "x2": 400, "y2": 352}},{"timestamp": "2024-01-30T19:07:59.841586", "age": 36, "gender": "Male", "bounding_box": {"x1": 165, "y1": 136, "x2": 423, "y2": 394}},{"timestamp": "2024-01-30T19:07:59.915619", "age": 33, "gender": "Male", "bounding_box": {"x1": 185, "y1": 137, "x2": 400, "y2": 352}},{"timestamp": "2024-01-30T19:07:59.982088", "age": 32, "gender": "Male", "bounding_box": {"x1": 185, "y1": 137, "x2": 400, "y2": 352}},{"timestamp": "2024-01-30T19:08:00.048185", "age": 32, "gender": "Male", "bounding_box": {"x1": 185, "y1": 137, "x2": 400, "y2": 352}},{"timestamp": "2024-01-30T19:08:00.114580", "age": 33, "gender": "Male", "bounding_box": {"x1": 185, "y1": 137, "x2": 400, "y2": 352}},{"timestamp": "2024-01-30T19:08:00.181103", "age": 32, "gender": "Male", "bounding_box": {"x1": 185, "y1": 137, "x2": 400, "y2": 352}},{"timestamp": "2024-01-30T19:08:00.255098", "age": 33, "gender": "Male", "bounding_box": {"x1": 185, "y1": 137, "x2": 400, "y2": 352}},{"timestamp": "2024-01-30T19:08:00.321445", "age": 35, "gender": "Male", "bounding_box": {"x1": 185, "y1": 137, "x2": 400, "y2": 352}},{"timestamp": "2024-01-30T19:08:00.387512", "age": 33, "gender": "Male", "bounding_box": {"x1": 185, "y1": 137, "x2": 400, "y2": 352}},{"timestamp": "2024-01-30T19:08:00.453814", "age": 35, "gender": "Male", "bounding_box": {"x1": 185, "y1": 137, "x2": 400, "y2": 352}},{"timestamp": "2024-01-30T19:08:00.520298", "age": 33, "gender": "Male", "bounding_box": {"x1": 185, "y1": 137, "x2": 400, "y2": 352}},{"timestamp": "2024-01-30T19:08:00.588198", "age": 35, "gender": "Male", "bounding_box": {"x1": 185, "y1": 137, "x2": 400, "y2": 352}},{"timestamp": "2024-01-30T19:08:00.654714", "age": 37, "gender": "Male", "bounding_box": {"x1": 185, "y1": 137, "x2": 400, "y2": 352}},{"timestamp": "2024-01-30T19:08:00.721069", "age": 35, "gender": "Male", "bounding_box": {"x1": 185, "y1": 137, "x2": 400, "y2": 352}},{"timestamp": "2024-01-30T19:08:00.786901", "age": 33, "gender": "Male", "bounding_box": {"x1": 185, "y1": 137, "x2": 400, "y2": 352}},{"timestamp": "2024-01-30T19:08:00.854081", "age": 33, "gender": "Male", "bounding_box": {"x1": 165, "y1": 136, "x2": 423, "y2": 394}},{"timestamp": "2024-01-30T19:08:00.921504", "age": 33, "gender": "Male", "bounding_box": {"x1": 165, "y1": 136, "x2": 423, "y2": 394}},{"timestamp": "2024-01-30T19:08:00.989707", "age": 34, "gender": "Male", "bounding_box": {"x1": 165, "y1": 136, "x2": 423, "y2": 394}},{"timestamp": "2024-01-30T19:08:01.057505", "age": 34, "gender": "Male", "bounding_box": {"x1": 185, "y1": 137, "x2": 400, "y2": 352}},{"timestamp": "2024-01-30T19:08:01.124189", "age": 35, "gender": "Male", "bounding_box": {"x1": 165, "y1": 136, "x2": 423, "y2": 394}},{"timestamp": "2024-01-30T19:08:01.190579", "age": 35, "gender": "Male", "bounding_box": {"x1": 165, "y1": 136, "x2": 423, "y2": 394}},{"timestamp": "2024-01-30T19:08:01.257014", "age": 37, "gender": "Male", "bounding_box": {"x1": 165, "y1": 136, "x2": 423, "y2": 394}},{"timestamp": "2024-01-30T19:08:01.325049", "age": 35, "gender": "Male", "bounding_box": {"x1": 165, "y1": 136, "x2": 423, "y2": 394}},{"timestamp": "2024-01-30T19:08:01.398083", "age": 35, "gender": "Male", "bounding_box": {"x1": 165, "y1": 136, "x2": 423, "y2": 394}},{"timestamp": "2024-01-30T19:08:01.468508", "age": 38, "gender": "Male", "bounding_box": {"x1": 165, "y1": 136, "x2": 423, "y2": 394}},{"timestamp": "2024-01-30T19:08:01.535386", "age": 37, "gender": "Male", "bounding_box": {"x1": 165, "y1": 136, "x2": 423, "y2": 394}},{"timestamp": "2024-01-30T19:08:01.601346", "age": 35, "gender": "Male", "bounding_box": {"x1": 165, "y1": 136, "x2": 423, "y2": 394}},{"timestamp": "2024-01-30T19:08:01.667760", "age": 34, "gender": "Male", "bounding_box": {"x1": 185, "y1": 137, "x2": 400, "y2": 352}},{"timestamp": "2024-01-30T19:08:01.734013", "age": 33, "gender": "Male", "bounding_box": {"x1": 165, "y1": 108, "x2": 423, "y2": 366}},{"timestamp": "2024-01-30T19:08:01.802765", "age": 33, "gender": "Male", "bounding_box": {"x1": 165, "y1": 108, "x2": 423, "y2": 366}},{"timestamp": "2024-01-30T19:08:01.869087", "age": 34, "gender": "Male", "bounding_box": {"x1": 165, "y1": 108, "x2": 423, "y2": 366}},{"timestamp": "2024-01-30T19:08:01.935541", "age": 34, "gender": "Male", "bounding_box": {"x1": 165, "y1": 108, "x2": 423, "y2": 366}},{"timestamp": "2024-01-30T19:08:02.001688", "age": 33, "gender": "Male", "bounding_box": {"x1": 165, "y1": 108, "x2": 423, "y2": 366}},{"timestamp": "2024-01-30T19:08:02.068538", "age": 34, "gender": "Male", "bounding_box": {"x1": 165, "y1": 108, "x2": 423, "y2": 366}},{"timestamp": "2024-01-30T19:08:02.138226", "age": 34, "gender": "Male", "bounding_box": {"x1": 165, "y1": 108, "x2": 423, "y2": 366}},{"timestamp": "2024-01-30T19:08:02.204609", "age": 35, "gender": "Male", "bounding_box": {"x1": 165, "y1": 108, "x2": 423, "y2": 366}},{"timestamp": "2024-01-30T19:08:02.270604", "age": 35, "gender": "Male", "bounding_box": {"x1": 165, "y1": 108, "x2": 423, "y2": 366}},{"timestamp": "2024-01-30T19:08:02.336721", "age": 34, "gender": "Male", "bounding_box": {"x1": 165, "y1": 108, "x2": 423, "y2": 366}},{"timestamp": "2024-01-30T19:08:02.403066", "age": 34, "gender": "Male", "bounding_box": {"x1": 165, "y1": 108, "x2": 423, "y2": 366}},{"timestamp": "2024-01-30T19:08:02.470420", "age": 34, "gender": "Male", "bounding_box": {"x1": 165, "y1": 108, "x2": 423, "y2": 366}},{"timestamp": "2024-01-30T19:08:02.537345", "age": 35, "gender": "Male", "bounding_box": {"x1": 165, "y1": 108, "x2": 423, "y2": 366}},{"timestamp": "2024-01-30T19:08:02.603907", "age": 35, "gender": "Male", "bounding_box": {"x1": 165, "y1": 108, "x2": 423, "y2": 366}},{"timestamp": "2024-01-30T19:08:02.681602", "age": 35, "gender": "Male", "bounding_box": {"x1": 165, "y1": 108, "x2": 423, "y2": 366}},{"timestamp": "2024-01-30T19:08:02.749252", "age": 34, "gender": "Male", "bounding_box": {"x1": 165, "y1": 108, "x2": 423, "y2": 366}},{"timestamp": "2024-01-30T19:08:02.815736", "age": 35, "gender": "Male", "bounding_box": {"x1": 165, "y1": 108, "x2": 423, "y2": 366}},{"timestamp": "2024-01-30T19:08:02.884281", "age": 34, "gender": "Male", "bounding_box": {"x1": 165, "y1": 108, "x2": 423, "y2": 366}},{"timestamp": "2024-01-30T19:08:02.968642", "age": 35, "gender": "Male", "bounding_box": {"x1": 165, "y1": 108, "x2": 423, "y2": 366}},{"timestamp": "2024-01-30T19:08:03.048750", "age": 34, "gender": "Male", "bounding_box": {"x1": 165, "y1": 108, "x2": 423, "y2": 366}},{"timestamp": "2024-01-30T19:08:03.133537", "age": 35, "gender": "Male", "bounding_box": {"x1": 165, "y1": 108, "x2": 423, "y2": 366}},{"timestamp": "2024-01-30T19:08:03.201006", "age": 35, "gender": "Male", "bounding_box": {"x1": 165, "y1": 108, "x2": 423, "y2": 366}},{"timestamp": "2024-01-30T19:08:03.268626", "age": 34, "gender": "Male", "bounding_box": {"x1": 165, "y1": 108, "x2": 423, "y2": 366}},{"timestamp": "2024-01-30T19:08:03.347711", "age": 33, "gender": "Male", "bounding_box": {"x1": 165, "y1": 108, "x2": 423, "y2": 366}},{"timestamp": "2024-01-30T19:08:03.420872", "age": 33, "gender": "Male", "bounding_box": {"x1": 165, "y1": 108, "x2": 423, "y2": 366}},{"timestamp": "2024-01-30T19:08:03.489727", "age": 33, "gender": "Male", "bounding_box": {"x1": 165, "y1": 108, "x2": 423, "y2": 366}},{"timestamp": "2024-01-30T19:08:03.561858", "age": 33, "gender": "Male", "bounding_box": {"x1": 165, "y1": 108, "x2": 423, "y2": 366}},{"timestamp": "2024-01-30T19:08:03.630667", "age": 34, "gender": "Male", "bounding_box": {"x1": 165, "y1": 108, "x2": 423, "y2": 366}},{"timestamp": "2024-01-30T19:08:03.699244", "age": 34, "gender": "Male", "bounding_box": {"x1": 165, "y1": 108, "x2": 423, "y2": 366}},{"timestamp": "2024-01-30T19:08:03.768983", "age": 33, "gender": "Male", "bounding_box": {"x1": 165, "y1": 108, "x2": 423, "y2": 366}},{"timestamp": "2024-01-30T19:08:03.836597", "age": 33, "gender": "Male", "bounding_box": {"x1": 165, "y1": 108, "x2": 423, "y2": 366}},{"timestamp": "2024-01-30T19:08:03.903736", "age": 34, "gender": "Male", "bounding_box": {"x1": 185, "y1": 113, "x2": 400, "y2": 328}},{"timestamp": "2024-01-30T19:08:03.970048", "age": 33, "gender": "Male", "bounding_box": {"x1": 185, "y1": 113, "x2": 400, "y2": 328}},{"timestamp": "2024-01-30T19:08:04.038410", "age": 33, "gender": "Male", "bounding_box": {"x1": 185, "y1": 113, "x2": 400, "y2": 328}},{"timestamp": "2024-01-30T19:08:04.104627", "age": 32, "gender": "Male", "bounding_box": {"x1": 185, "y1": 113, "x2": 400, "y2": 328}},{"timestamp": "2024-01-30T19:08:04.170858", "age": 32, "gender": "Male", "bounding_box": {"x1": 185, "y1": 113, "x2": 400, "y2": 328}},{"timestamp": "2024-01-30T19:08:04.236710", "age": 32, "gender": "Male", "bounding_box": {"x1": 185, "y1": 113, "x2": 400, "y2": 328}},{"timestamp": "2024-01-30T19:08:04.303242", "age": 32, "gender": "Male", "bounding_box": {"x1": 185, "y1": 113, "x2": 400, "y2": 328}},{"timestamp": "2024-01-30T19:08:04.369557", "age": 30, "gender": "Male", "bounding_box": {"x1": 185, "y1": 113, "x2": 400, "y2": 328}},{"timestamp": "2024-01-30T19:08:04.435714", "age": 31, "gender": "Male", "bounding_box": {"x1": 185, "y1": 113, "x2": 400, "y2": 328}},{"timestamp": "2024-01-30T19:08:04.503888", "age": 32, "gender": "Male", "bounding_box": {"x1": 185, "y1": 113, "x2": 400, "y2": 328}},{"timestamp": "2024-01-30T19:08:04.571230", "age": 31, "gender": "Male", "bounding_box": {"x1": 185, "y1": 113, "x2": 400, "y2": 328}},{"timestamp": "2024-01-30T19:08:04.645892", "age": 31, "gender": "Male", "bounding_box": {"x1": 185, "y1": 113, "x2": 400, "y2": 328}},{"timestamp": "2024-01-30T19:08:04.713884", "age": 32, "gender": "Male", "bounding_box": {"x1": 185, "y1": 113, "x2": 400, "y2": 328}},{"timestamp": "2024-01-30T19:08:04.780721", "age": 31, "gender": "Male", "bounding_box": {"x1": 185, "y1": 113, "x2": 400, "y2": 328}},{"timestamp": "2024-01-30T19:08:04.847669", "age": 30, "gender": "Male", "bounding_box": {"x1": 185, "y1": 113, "x2": 400, "y2": 328}},{"timestamp": "2024-01-30T19:08:04.914527", "age": 31, "gender": "Male", "bounding_box": {"x1": 185, "y1": 113, "x2": 400, "y2": 328}},{"timestamp": "2024-01-30T19:08:04.981587", "age": 30, "gender": "Male", "bounding_box": {"x1": 185, "y1": 113, "x2": 400, "y2": 328}},{"timestamp": "2024-01-30T19:08:05.049674", "age": 30, "gender": "Male", "bounding_box": {"x1": 185, "y1": 113, "x2": 400, "y2": 328}},{"timestamp": "2024-01-30T19:08:05.125027", "age": 32, "gender": "Male", "bounding_box": {"x1": 185, "y1": 113, "x2": 400, "y2": 328}},{"timestamp": "2024-01-30T19:08:05.191540", "age": 36, "gender": "Male", "bounding_box": {"x1": 185, "y1": 113, "x2": 400, "y2": 328}},{"timestamp": "2024-01-30T19:08:05.258352", "age": 37, "gender": "Male", "bounding_box": {"x1": 185, "y1": 113, "x2": 400, "y2": 328}},{"timestamp": "2024-01-30T19:08:05.324965", "age": 37, "gender": "Male", "bounding_box": {"x1": 185, "y1": 113, "x2": 400, "y2": 328}},{"timestamp": "2024-01-30T19:08:05.391501", "age": 37, "gender": "Male", "bounding_box": {"x1": 185, "y1": 113, "x2": 400, "y2": 328}},{"timestamp": "2024-01-30T19:08:05.457937", "age": 37, "gender": "Male", "bounding_box": {"x1": 165, "y1": 79, "x2": 423, "y2": 337}},{"timestamp": "2024-01-30T19:08:05.524623", "age": 35, "gender": "Male", "bounding_box": {"x1": 209, "y1": 90, "x2": 424, "y2": 305}},{"timestamp": "2024-01-30T19:08:05.591469", "age": 34, "gender": "Male", "bounding_box": {"x1": 209, "y1": 90, "x2": 424, "y2": 305}},{"timestamp": "2024-01-30T19:08:05.658492", "age": 29, "gender": "Male", "bounding_box": {"x1": 209, "y1": 90, "x2": 424, "y2": 305}},{"timestamp": "2024-01-30T19:08:05.725145", "age": 27, "gender": "Male", "bounding_box": {"x1": 194, "y1": 79, "x2": 452, "y2": 337}},{"timestamp": "2024-01-30T19:08:05.793445", "age": 30, "gender": "Male", "bounding_box": {"x1": 233, "y1": 90, "x2": 448, "y2": 305}},{"timestamp": "2024-01-30T19:08:06.649214", "age": 26, "gender": "Male", "bounding_box": {"x1": 233, "y1": 161, "x2": 448, "y2": 376}},{"timestamp": "2024-01-30T19:08:06.716319", "age": 35, "gender": "Male", "bounding_box": {"x1": 209, "y1": 161, "x2": 424, "y2": 376}},{"timestamp": "2024-01-30T19:08:06.782531", "age": 34, "gender": "Male", "bounding_box": {"x1": 185, "y1": 161, "x2": 400, "y2": 376}},{"timestamp": "2024-01-30T19:08:06.848264", "age": 36, "gender": "Male", "bounding_box": {"x1": 161, "y1": 185, "x2": 376, "y2": 400}},{"timestamp": "2024-01-30T19:08:06.914888", "age": 29, "gender": "Male", "bounding_box": {"x1": 137, "y1": 161, "x2": 352, "y2": 376}},{"timestamp": "2024-01-30T19:08:06.982872", "age": 28, "gender": "Male", "bounding_box": {"x1": 113, "y1": 161, "x2": 328, "y2": 376}},{"timestamp": "2024-01-30T19:08:07.053745", "age": 34, "gender": "Male", "bounding_box": {"x1": 90, "y1": 161, "x2": 305, "y2": 376}},{"timestamp": "2024-01-30T19:09:44.672216", "age": 28, "gender": "Female", "bounding_box": {"x1": 285, "y1": 304, "x2": 371, "y2": 390}},{"timestamp": "2024-01-30T19:09:46.356090", "age": 28, "gender": "Female", "bounding_box": {"x1": 285, "y1": 317, "x2": 357, "y2": 389}},{"timestamp": "2024-01-30T19:10:13.485040", "age": 36, "gender": "Male", "bounding_box": {"x1": 165, "y1": 22, "x2": 423, "y2": 280}},{"timestamp": "2024-01-30T19:10:13.556321", "age": 28, "gender": "Male", "bounding_box": {"x1": 130, "y1": 26, "x2": 439, "y2": 336}},{"timestamp": "2024-01-30T19:10:13.627161", "age": 31, "gender": "Male", "bounding_box": {"x1": 130, "y1": 61, "x2": 439, "y2": 370}},{"timestamp": "2024-01-30T19:10:13.702805", "age": 30, "gender": "Male", "bounding_box": {"x1": 130, "y1": 61, "x2": 439, "y2": 370}},{"timestamp": "2024-01-30T19:10:13.770314", "age": 28, "gender": "Male", "bounding_box": {"x1": 130, "y1": 61, "x2": 439, "y2": 370}},{"timestamp": "2024-01-30T19:10:13.840157", "age": 29, "gender": "Male", "bounding_box": {"x1": 130, "y1": 61, "x2": 439, "y2": 370}},{"timestamp": "2024-01-30T19:10:13.912032", "age": 38, "gender": "Male", "bounding_box": {"x1": 130, "y1": 61, "x2": 439, "y2": 370}},{"timestamp": "2024-01-30T19:10:13.983140", "age": 33, "gender": "Male", "bounding_box": {"x1": 130, "y1": 61, "x2": 439, "y2": 370}},{"timestamp": "2024-01-30T19:10:14.052138", "age": 33, "gender": "Male", "bounding_box": {"x1": 130, "y1": 61, "x2": 439, "y2": 370}},{"timestamp": "2024-01-30T19:10:14.120291", "age": 36, "gender": "Male", "bounding_box": {"x1": 130, "y1": 61, "x2": 439, "y2": 370}},{"timestamp": "2024-01-30T19:10:14.189762", "age": 31, "gender": "Male", "bounding_box": {"x1": 130, "y1": 95, "x2": 439, "y2": 405}},{"timestamp": "2024-01-30T19:10:14.257593", "age": 38, "gender": "Male", "bounding_box": {"x1": 165, "y1": 108, "x2": 423, "y2": 366}},{"timestamp": "2024-01-30T19:10:14.325188", "age": 36, "gender": "Male", "bounding_box": {"x1": 165, "y1": 108, "x2": 423, "y2": 366}},{"timestamp": "2024-01-30T19:10:14.392633", "age": 37, "gender": "Male", "bounding_box": {"x1": 165, "y1": 108, "x2": 423, "y2": 366}},{"timestamp": "2024-01-30T19:10:14.459955", "age": 39, "gender": "Male", "bounding_box": {"x1": 130, "y1": 61, "x2": 439, "y2": 370}},{"timestamp": "2024-01-30T19:10:14.527624", "age": 39, "gender": "Male", "bounding_box": {"x1": 165, "y1": 79, "x2": 423, "y2": 337}},{"timestamp": "2024-01-30T19:10:14.594510", "age": 40, "gender": "Male", "bounding_box": {"x1": 130, "y1": 61, "x2": 439, "y2": 370}},{"timestamp": "2024-01-30T19:10:14.661697", "age": 39, "gender": "Male", "bounding_box": {"x1": 130, "y1": 61, "x2": 439, "y2": 370}},{"timestamp": "2024-01-30T19:10:14.730270", "age": 39, "gender": "Male", "bounding_box": {"x1": 130, "y1": 61, "x2": 439, "y2": 370}},{"timestamp": "2024-01-30T19:10:14.797915", "age": 37, "gender": "Male", "bounding_box": {"x1": 130, "y1": 61, "x2": 439, "y2": 370}},{"timestamp": "2024-01-30T19:10:14.867018", "age": 37, "gender": "Male", "bounding_box": {"x1": 130, "y1": 61, "x2": 439, "y2": 370}},{"timestamp": "2024-01-30T19:10:14.935323", "age": 35, "gender": "Male", "bounding_box": {"x1": 165, "y1": 108, "x2": 423, "y2": 366}},{"timestamp": "2024-01-30T19:10:15.003298", "age": 35, "gender": "Male", "bounding_box": {"x1": 165, "y1": 50, "x2": 423, "y2": 308}},{"timestamp": "2024-01-30T19:10:15.070665", "age": 50, "gender": "Male", "bounding_box": {"x1": 165, "y1": 22, "x2": 423, "y2": 280}},{"timestamp": "2024-01-30T19:11:23.295480", "age": 37, "gender": "Male", "bounding_box": {"x1": 233, "y1": 42, "x2": 448, "y2": 257}},{"timestamp": "2024-01-30T19:11:23.366387", "age": 37, "gender": "Male", "bounding_box": {"x1": 233, "y1": 42, "x2": 448, "y2": 257}},{"timestamp": "2024-01-30T19:11:24.120329", "age": 36, "gender": "Male", "bounding_box": {"x1": 164, "y1": 26, "x2": 474, "y2": 336}},{"timestamp": "2024-01-30T19:11:24.189623", "age": 36, "gender": "Male", "bounding_box": {"x1": 164, "y1": 26, "x2": 474, "y2": 336}},{"timestamp": "2024-01-30T19:11:24.261188", "age": 37, "gender": "Male", "bounding_box": {"x1": 164, "y1": 26, "x2": 474, "y2": 336}},{"timestamp": "2024-01-30T19:11:24.333276", "age": 36, "gender": "Male", "bounding_box": {"x1": 164, "y1": 26, "x2": 474, "y2": 336}},{"timestamp": "2024-01-30T19:11:24.404351", "age": 35, "gender": "Male", "bounding_box": {"x1": 164, "y1": 61, "x2": 474, "y2": 370}},{"timestamp": "2024-01-30T19:11:24.473303", "age": 36, "gender": "Male", "bounding_box": {"x1": 164, "y1": 61, "x2": 474, "y2": 370}},{"timestamp": "2024-01-30T19:11:24.544857", "age": 37, "gender": "Male", "bounding_box": {"x1": 115, "y1": 32, "x2": 486, "y2": 404}},{"timestamp": "2024-01-30T19:11:24.613926", "age": 38, "gender": "Male", "bounding_box": {"x1": 115, "y1": 32, "x2": 486, "y2": 404}},{"timestamp": "2024-01-30T19:11:24.682119", "age": 39, "gender": "Male", "bounding_box": {"x1": 130, "y1": 61, "x2": 439, "y2": 370}},{"timestamp": "2024-01-30T19:11:24.751304", "age": 39, "gender": "Male", "bounding_box": {"x1": 130, "y1": 61, "x2": 439, "y2": 370}},{"timestamp": "2024-01-30T19:11:24.822020", "age": 39, "gender": "Male", "bounding_box": {"x1": 130, "y1": 61, "x2": 439, "y2": 370}},{"timestamp": "2024-01-30T19:11:24.891547", "age": 37, "gender": "Male", "bounding_box": {"x1": 130, "y1": 61, "x2": 439, "y2": 370}},{"timestamp": "2024-01-30T19:11:24.959711", "age": 37, "gender": "Male", "bounding_box": {"x1": 73, "y1": 73, "x2": 445, "y2": 445}},{"timestamp": "2024-01-30T19:11:25.030754", "age": 36, "gender": "Male", "bounding_box": {"x1": 73, "y1": 73, "x2": 445, "y2": 445}},{"timestamp": "2024-01-30T19:11:25.103179", "age": 37, "gender": "Male", "bounding_box": {"x1": 95, "y1": 95, "x2": 405, "y2": 405}},{"timestamp": "2024-01-30T19:11:25.172215", "age": 35, "gender": "Male", "bounding_box": {"x1": 95, "y1": 95, "x2": 405, "y2": 405}},{"timestamp": "2024-01-30T19:11:25.243555", "age": 34, "gender": "Male", "bounding_box": {"x1": 95, "y1": 95, "x2": 405, "y2": 405}},{"timestamp": "2024-01-30T19:11:25.316417", "age": 35, "gender": "Male", "bounding_box": {"x1": 95, "y1": 95, "x2": 405, "y2": 405}},{"timestamp": "2024-01-30T19:11:25.390803", "age": 35, "gender": "Male", "bounding_box": {"x1": 95, "y1": 95, "x2": 405, "y2": 405}},{"timestamp": "2024-01-30T19:11:25.459658", "age": 34, "gender": "Male", "bounding_box": {"x1": 73, "y1": 73, "x2": 445, "y2": 445}},{"timestamp": "2024-01-30T19:11:25.529705", "age": 35, "gender": "Male", "bounding_box": {"x1": 130, "y1": 61, "x2": 439, "y2": 370}},{"timestamp": "2024-01-30T19:11:25.598472", "age": 35, "gender": "Male", "bounding_box": {"x1": 130, "y1": 61, "x2": 439, "y2": 370}},{"timestamp": "2024-01-30T19:11:25.667605", "age": 35, "gender": "Male", "bounding_box": {"x1": 130, "y1": 61, "x2": 439, "y2": 370}},{"timestamp": "2024-01-30T19:11:25.735957", "age": 35, "gender": "Male", "bounding_box": {"x1": 130, "y1": 61, "x2": 439, "y2": 370}},{"timestamp": "2024-01-30T19:11:25.804863", "age": 35, "gender": "Male", "bounding_box": {"x1": 130, "y1": 95, "x2": 439, "y2": 405}},{"timestamp": "2024-01-30T19:11:25.873218", "age": 35, "gender": "Male", "bounding_box": {"x1": 73, "y1": 73, "x2": 445, "y2": 445}},{"timestamp": "2024-01-30T19:11:25.942792", "age": 44, "gender": "Male", "bounding_box": {"x1": 73, "y1": 73, "x2": 445, "y2": 445}},{"timestamp": "2024-01-30T19:11:26.010424", "age": 49, "gender": "Male", "bounding_box": {"x1": 73, "y1": 73, "x2": 445, "y2": 445}},{"timestamp": "2024-01-30T19:11:26.078517", "age": 41, "gender": "Male", "bounding_box": {"x1": 95, "y1": 95, "x2": 405, "y2": 405}},{"timestamp": "2024-01-30T19:11:26.146111", "age": 50, "gender": "Male", "bounding_box": {"x1": 73, "y1": 73, "x2": 445, "y2": 445}},{"timestamp": "2024-01-30T19:11:27.635274", "age": 47, "gender": "Male", "bounding_box": {"x1": 161, "y1": 233, "x2": 376, "y2": 448}},{"timestamp": "2024-01-30T19:11:27.736443", "age": 37, "gender": "Male", "bounding_box": {"x1": 185, "y1": 185, "x2": 400, "y2": 400}},{"timestamp": "2024-01-30T19:11:27.802737", "age": 32, "gender": "Male", "bounding_box": {"x1": 214, "y1": 174, "x2": 393, "y2": 353}},{"timestamp": "2024-01-30T19:11:27.869714", "age": 28, "gender": "Male", "bounding_box": {"x1": 214, "y1": 154, "x2": 393, "y2": 333}},{"timestamp": "2024-01-30T19:11:27.937754", "age": 29, "gender": "Male", "bounding_box": {"x1": 234, "y1": 134, "x2": 413, "y2": 313}},{"timestamp": "2024-01-30T19:11:28.005154", "age": 35, "gender": "Male", "bounding_box": {"x1": 234, "y1": 134, "x2": 413, "y2": 313}},{"timestamp": "2024-01-30T19:11:28.073281", "age": 33, "gender": "Male", "bounding_box": {"x1": 234, "y1": 114, "x2": 413, "y2": 293}},{"timestamp": "2024-01-30T19:11:28.141141", "age": 36, "gender": "Male", "bounding_box": {"x1": 234, "y1": 114, "x2": 413, "y2": 293}},{"timestamp": "2024-01-30T19:11:28.209593", "age": 34, "gender": "Male", "bounding_box": {"x1": 234, "y1": 114, "x2": 413, "y2": 293}},{"timestamp": "2024-01-30T19:11:28.277723", "age": 33, "gender": "Male", "bounding_box": {"x1": 261, "y1": 112, "x2": 410, "y2": 261}},{"timestamp": "2024-01-30T19:11:28.345871", "age": 36, "gender": "Male", "bounding_box": {"x1": 261, "y1": 128, "x2": 410, "y2": 277}},{"timestamp": "2024-01-30T19:11:30.105824", "age": 43, "gender": "Male", "bounding_box": {"x1": 194, "y1": 194, "x2": 452, "y2": 452}},{"timestamp": "2024-01-30T19:11:30.172722", "age": 43, "gender": "Male", "bounding_box": {"x1": 164, "y1": 164, "x2": 474, "y2": 474}},{"timestamp": "2024-01-30T19:11:30.240224", "age": 36, "gender": "Male", "bounding_box": {"x1": 194, "y1": 165, "x2": 452, "y2": 423}},{"timestamp": "2024-01-30T19:11:31.537840", "age": 41, "gender": "Male", "bounding_box": {"x1": 194, "y1": 136, "x2": 452, "y2": 394}},{"timestamp": "2024-01-30T19:11:31.612287", "age": 39, "gender": "Male", "bounding_box": {"x1": 194, "y1": 136, "x2": 452, "y2": 394}},{"timestamp": "2024-01-30T19:11:31.680912", "age": 35, "gender": "Male", "bounding_box": {"x1": 194, "y1": 165, "x2": 452, "y2": 423}},{"timestamp": "2024-01-30T19:11:31.756504", "age": 33, "gender": "Male", "bounding_box": {"x1": 164, "y1": 130, "x2": 474, "y2": 439}},{"timestamp": "2024-01-30T19:11:31.824709", "age": 32, "gender": "Male", "bounding_box": {"x1": 164, "y1": 130, "x2": 474, "y2": 439}},{"timestamp": "2024-01-30T19:11:31.893040", "age": 36, "gender": "Male", "bounding_box": {"x1": 164, "y1": 130, "x2": 474, "y2": 439}},{"timestamp": "2024-01-30T19:11:31.970359", "age": 36, "gender": "Male", "bounding_box": {"x1": 194, "y1": 136, "x2": 452, "y2": 394}},{"timestamp": "2024-01-30T19:11:32.037968", "age": 37, "gender": "Male", "bounding_box": {"x1": 194, "y1": 136, "x2": 452, "y2": 394}},{"timestamp": "2024-01-30T19:11:32.110784", "age": 39, "gender": "Male", "bounding_box": {"x1": 194, "y1": 136, "x2": 452, "y2": 394}},{"timestamp": "2024-01-30T19:12:05.401820", "age": 49, "gender": "Male", "bounding_box": {"x1": 194, "y1": 194, "x2": 452, "y2": 452}},{"timestamp": "2024-01-30T19:12:05.470589", "age": 47, "gender": "Male", "bounding_box": {"x1": 194, "y1": 194, "x2": 452, "y2": 452}},{"timestamp": "2024-01-30T19:12:05.541561", "age": 47, "gender": "Male", "bounding_box": {"x1": 194, "y1": 194, "x2": 452, "y2": 452}},{"timestamp": "2024-01-30T19:12:05.611473", "age": 45, "gender": "Male", "bounding_box": {"x1": 194, "y1": 194, "x2": 452, "y2": 452}},{"timestamp": "2024-01-30T19:12:05.680337", "age": 39, "gender": "Male", "bounding_box": {"x1": 194, "y1": 194, "x2": 452, "y2": 452}},{"timestamp": "2024-01-30T19:12:05.748332", "age": 36, "gender": "Male", "bounding_box": {"x1": 194, "y1": 194, "x2": 452, "y2": 452}},{"timestamp": "2024-01-30T19:12:05.816775", "age": 37, "gender": "Male", "bounding_box": {"x1": 194, "y1": 194, "x2": 452, "y2": 452}},{"timestamp": "2024-01-30T19:12:05.885438", "age": 36, "gender": "Male", "bounding_box": {"x1": 194, "y1": 194, "x2": 452, "y2": 452}},{"timestamp": "2024-01-30T19:12:05.954099", "age": 38, "gender": "Male", "bounding_box": {"x1": 194, "y1": 194, "x2": 452, "y2": 452}},{"timestamp": "2024-01-30T19:12:06.022099", "age": 41, "gender": "Male", "bounding_box": {"x1": 194, "y1": 194, "x2": 452, "y2": 452}},{"timestamp": "2024-01-30T19:12:07.588034", "age": 38, "gender": "Male", "bounding_box": {"x1": 194, "y1": 194, "x2": 452, "y2": 452}},{"timestamp": "2024-01-30T19:12:07.659791", "age": 41, "gender": "Male", "bounding_box": {"x1": 194, "y1": 194, "x2": 452, "y2": 452}},{"timestamp": "2024-01-30T19:12:07.728824", "age": 40, "gender": "Male", "bounding_box": {"x1": 194, "y1": 194, "x2": 452, "y2": 452}},{"timestamp": "2024-01-30T19:12:07.798375", "age": 42, "gender": "Male", "bounding_box": {"x1": 194, "y1": 194, "x2": 452, "y2": 452}},{"timestamp": "2024-01-30T19:12:07.867416", "age": 45, "gender": "Male", "bounding_box": {"x1": 194, "y1": 194, "x2": 452, "y2": 452}},{"timestamp": "2024-01-30T19:12:07.935192", "age": 43, "gender": "Male", "bounding_box": {"x1": 194, "y1": 194, "x2": 452, "y2": 452}},{"timestamp": "2024-01-30T19:12:12.408832", "age": 34, "gender": "Male", "bounding_box": {"x1": 194, "y1": 194, "x2": 452, "y2": 452}},{"timestamp": "2024-01-30T19:12:12.480785", "age": 35, "gender": "Male", "bounding_box": {"x1": 194, "y1": 194, "x2": 452, "y2": 452}},{"timestamp": "2024-01-30T19:12:12.552438", "age": 37, "gender": "Male", "bounding_box": {"x1": 194, "y1": 194, "x2": 452, "y2": 452}},{"timestamp": "2024-01-30T19:12:13.016453", "age": 39, "gender": "Male", "bounding_box": {"x1": 164, "y1": 164, "x2": 474, "y2": 474}},{"timestamp": "2024-01-30T19:13:05.073517", "age": 33, "gender": "Male", "bounding_box": {"x1": 164, "y1": 198, "x2": 474, "y2": 508}},{"timestamp": "2024-01-30T19:13:05.139753", "age": 32, "gender": "Male", "bounding_box": {"x1": 164, "y1": 198, "x2": 474, "y2": 508}},{"timestamp": "2024-01-30T19:13:05.206623", "age": 38, "gender": "Male", "bounding_box": {"x1": 194, "y1": 194, "x2": 452, "y2": 452}},{"timestamp": "2024-01-30T19:13:05.273592", "age": 39, "gender": "Male", "bounding_box": {"x1": 194, "y1": 194, "x2": 452, "y2": 452}},{"timestamp": "2024-01-30T19:13:05.342205", "age": 36, "gender": "Male", "bounding_box": {"x1": 194, "y1": 194, "x2": 452, "y2": 452}},{"timestamp": "2024-01-30T19:13:25.226137", "age": 32, "gender": "Male", "bounding_box": {"x1": 95, "y1": 198, "x2": 405, "y2": 508}},{"timestamp": "2024-01-30T19:13:25.360718", "age": 31, "gender": "Male", "bounding_box": {"x1": 130, "y1": 198, "x2": 439, "y2": 508}},{"timestamp": "2024-01-30T19:13:25.428323", "age": 31, "gender": "Male", "bounding_box": {"x1": 130, "y1": 198, "x2": 439, "y2": 508}},{"timestamp": "2024-01-30T19:13:25.494009", "age": 31, "gender": "Male", "bounding_box": {"x1": 165, "y1": 222, "x2": 423, "y2": 480}},{"timestamp": "2024-01-30T19:13:25.561944", "age": 31, "gender": "Male", "bounding_box": {"x1": 165, "y1": 222, "x2": 423, "y2": 480}},{"timestamp": "2024-01-30T19:13:25.628397", "age": 31, "gender": "Male", "bounding_box": {"x1": 165, "y1": 194, "x2": 423, "y2": 452}},{"timestamp": "2024-01-30T19:13:25.730049", "age": 33, "gender": "Male", "bounding_box": {"x1": 194, "y1": 194, "x2": 452, "y2": 452}},{"timestamp": "2024-01-30T19:13:25.796653", "age": 41, "gender": "Male", "bounding_box": {"x1": 164, "y1": 164, "x2": 474, "y2": 474}},{"timestamp": "2024-01-30T19:13:25.864767", "age": 38, "gender": "Male", "bounding_box": {"x1": 194, "y1": 194, "x2": 452, "y2": 452}},{"timestamp": "2024-01-30T19:13:25.933201", "age": 41, "gender": "Male", "bounding_box": {"x1": 194, "y1": 194, "x2": 452, "y2": 452}},{"timestamp": "2024-01-30T19:13:26.002116", "age": 36, "gender": "Male", "bounding_box": {"x1": 194, "y1": 194, "x2": 452, "y2": 452}},{"timestamp": "2024-01-30T19:13:26.070000", "age": 40, "gender": "Male", "bounding_box": {"x1": 194, "y1": 194, "x2": 452, "y2": 452}},{"timestamp": "2024-01-30T19:13:26.138094", "age": 39, "gender": "Male", "bounding_box": {"x1": 194, "y1": 194, "x2": 452, "y2": 452}},{"timestamp": "2024-01-30T19:13:26.204987", "age": 35, "gender": "Male", "bounding_box": {"x1": 194, "y1": 194, "x2": 452, "y2": 452}},{"timestamp": "2024-01-30T19:13:26.273565", "age": 42, "gender": "Male", "bounding_box": {"x1": 164, "y1": 164, "x2": 474, "y2": 474}},{"timestamp": "2024-01-30T19:13:26.341736", "age": 40, "gender": "Male", "bounding_box": {"x1": 194, "y1": 194, "x2": 452, "y2": 452}},{"timestamp": "2024-01-30T19:13:26.408676", "age": 39, "gender": "Male", "bounding_box": {"x1": 194, "y1": 194, "x2": 452, "y2": 452}},{"timestamp": "2024-01-30T19:13:26.476006", "age": 37, "gender": "Male", "bounding_box": {"x1": 194, "y1": 194, "x2": 452, "y2": 452}},{"timestamp": "2024-01-30T19:13:26.544961", "age": 38, "gender": "Male", "bounding_box": {"x1": 194, "y1": 194, "x2": 452, "y2": 452}},{"timestamp": "2024-01-30T19:13:26.614289", "age": 35, "gender": "Male", "bounding_box": {"x1": 194, "y1": 194, "x2": 452, "y2": 452}},{"timestamp": "2024-01-30T19:13:26.682142", "age": 35, "gender": "Male", "bounding_box": {"x1": 194, "y1": 194, "x2": 452, "y2": 452}},{"timestamp": "2024-01-30T19:13:26.748802", "age": 34, "gender": "Male", "bounding_box": {"x1": 194, "y1": 194, "x2": 452, "y2": 452}},{"timestamp": "2024-01-30T19:13:26.819150", "age": 38, "gender": "Male", "bounding_box": {"x1": 194, "y1": 194, "x2": 452, "y2": 452}},{"timestamp": "2024-01-30T19:13:26.885613", "age": 35, "gender": "Male", "bounding_box": {"x1": 194, "y1": 194, "x2": 452, "y2": 452}},{"timestamp": "2024-01-30T19:13:26.951812", "age": 38, "gender": "Male", "bounding_box": {"x1": 194, "y1": 194, "x2": 452, "y2": 452}},{"timestamp": "2024-01-30T19:13:27.018168", "age": 39, "gender": "Male", "bounding_box": {"x1": 194, "y1": 194, "x2": 452, "y2": 452}},{"timestamp": "2024-01-30T19:13:27.084574", "age": 39, "gender": "Male", "bounding_box": {"x1": 194, "y1": 194, "x2": 452, "y2": 452}},{"timestamp": "2024-01-30T19:13:27.155436", "age": 41, "gender": "Male", "bounding_box": {"x1": 194, "y1": 194, "x2": 452, "y2": 452}},{"timestamp": "2024-01-30T19:13:27.223785", "age": 39, "gender": "Male", "bounding_box": {"x1": 194, "y1": 194, "x2": 452, "y2": 452}},{"timestamp": "2024-01-30T19:13:27.290681", "age": 37, "gender": "Male", "bounding_box": {"x1": 194, "y1": 194, "x2": 452, "y2": 452}},{"timestamp": "2024-01-30T19:13:27.358889", "age": 37, "gender": "Male", "bounding_box": {"x1": 194, "y1": 194, "x2": 452, "y2": 452}},{"timestamp": "2024-01-30T19:13:27.425608", "age": 38, "gender": "Male", "bounding_box": {"x1": 194, "y1": 194, "x2": 452, "y2": 452}},{"timestamp": "2024-01-30T19:13:27.493795", "age": 41, "gender": "Male", "bounding_box": {"x1": 194, "y1": 194, "x2": 452, "y2": 452}},{"timestamp": "2024-01-30T19:13:27.568629", "age": 39, "gender": "Male", "bounding_box": {"x1": 194, "y1": 194, "x2": 452, "y2": 452}},{"timestamp": "2024-01-30T19:13:27.639161", "age": 41, "gender": "Male", "bounding_box": {"x1": 194, "y1": 194, "x2": 452, "y2": 452}},{"timestamp": "2024-01-30T19:13:27.706131", "age": 38, "gender": "Male", "bounding_box": {"x1": 194, "y1": 194, "x2": 452, "y2": 452}},{"timestamp": "2024-01-30T19:13:27.773363", "age": 41, "gender": "Male", "bounding_box": {"x1": 194, "y1": 194, "x2": 452, "y2": 452}},{"timestamp": "2024-01-30T19:14:27.037602", "age": 47, "gender": "Male", "bounding_box": {"x1": 194, "y1": 222, "x2": 452, "y2": 480}}